{
  "/_not-found/page": "app/_not-found/page.js",
  "/api/marketplace/listings/route": "app/api/marketplace/listings/route.js",
  "/api/marketplace/sign/route": "app/api/marketplace/sign/route.js",
  "/api/nft/mint/route": "app/api/nft/mint/route.js",
  "/api/singers/[id]/route": "app/api/singers/[id]/route.js",
  "/api/nft/collections/route": "app/api/nft/collections/route.js",
  "/api/distribution/publish/route": "app/api/distribution/publish/route.js",
  "/api/tracks/generate/route": "app/api/tracks/generate/route.js",
  "/api/singers/route": "app/api/singers/route.js",
  "/fan/page": "app/fan/page.js",
  "/api/singers/my/route": "app/api/singers/my/route.js",
  "/coach/page": "app/coach/page.js",
  "/page": "app/page.js",
  "/portal/page": "app/portal/page.js",
  "/api/tracks/my/route": "app/api/tracks/my/route.js",
  "/api/analytics/dashboard/route": "app/api/analytics/dashboard/route.js",
  "/producer/earnings/page": "app/producer/earnings/page.js",
  "/producer/studio/page": "app/producer/studio/page.js",
  "/producer/distribution/page": "app/producer/distribution/page.js",
  "/producer/incubator/page": "app/producer/incubator/page.js",
  "/producer/page": "app/producer/page.js",
  "/producer/mint/page": "app/producer/mint/page.js",
  "/producer/overview/page": "app/producer/overview/page.js"
}